dx_base/__init__.py
dx_base/exceptions.py
dx_base/forces.py
dx_base/materials.py
dx_base/safety_factors.py
dx_base/elements/__init__.py
dx_base-1.0.1.dist-info/LICENSE
dx_base-1.0.1.dist-info/METADATA
dx_base-1.0.1.dist-info/WHEEL
dx_base-1.0.1.dist-info/top_level.txt
dx_base-1.0.1.dist-info/RECORD
