Metadata-Version: 2.1
Name: dx-base
Version: 1.0.1
Summary: Base package for structural design software packages
Home-page: https://gitlab.com/d-e/dx-base
Author: Konstantinos Demartinos
Author-email: kostas@d-e.gr
Maintainer: demetriou engineering ltd.
Maintainer-email: kostas@d-e.gr
License: AGPLv3+
Keywords: structural-design
Platform: UNKNOWN
Classifier: Programming Language :: Python :: 3
Classifier: License :: OSI Approved :: GNU Affero General Public License v3 or later (AGPLv3+)
Classifier: Operating System :: OS Independent
Classifier: Topic :: Scientific/Engineering
Requires-Dist: dx-utilities (<2.0.0,>=1.0.0)
